sim_math/__init__.py
sim_math/simple_addition.py
sim_mat-1.0.0.dist-info/LICENSE.txt
sim_mat-1.0.0.dist-info/METADATA
sim_mat-1.0.0.dist-info/WHEEL
sim_mat-1.0.0.dist-info/top_level.txt
sim_mat-1.0.0.dist-info/RECORD
